{"nodes": [{"id": "c_users_taraz_uno_family_lib_features_friends_presentation_friends_screen_dart", "label": "friends_screen.dart", "file_type": "code", "source_file": "features/friends/presentation/friends_screen.dart", "source_location": null}, {"id": "presentation_friends_screen_friendsscreen", "label": "FriendsScreen", "file_type": "code", "source_file": "features/friends/presentation/friends_screen.dart", "source_location": null}, {"id": "consumerwidget", "label": "ConsumerWidget", "file_type": "code", "source_file": null, "source_location": null}, {"id": "friendscontrollerprovider", "label": "friendsControllerProvider", "file_type": "code", "source_file": null, "source_location": null}, {"id": "authcontrollerprovider", "label": "authControllerProvider", "file_type": "code", "source_file": null, "source_location": null}, {"id": "presentation_friends_screen_friendtile", "label": "_FriendTile", "file_type": "code", "source_file": "features/friends/presentation/friends_screen.dart", "source_location": null}, {"id": "statelesswidget", "label": "StatelessWidget", "file_type": "code", "source_file": null, "source_location": null}, {"id": "presentation_friends_screen_addfrienddialog", "label": "_AddFriendDialog", "file_type": "code", "source_file": "features/friends/presentation/friends_screen.dart", "source_location": null}, {"id": "statefulwidget", "label": "StatefulWidget", "file_type": "code", "source_file": null, "source_location": null}, {"id": "presentation_friends_screen_addfrienddialogstate", "label": "_AddFriendDialogState", "file_type": "code", "source_file": "features/friends/presentation/friends_screen.dart", "source_location": null}, {"id": "state", "label": "State", "file_type": "code", "source_file": null, "source_location": null}, {"id": "addfrienddialog", "label": "_AddFriendDialog", "file_type": "code", "source_file": null, "source_location": null}, {"id": "presentation_friends_screen_friend", "label": "friend", "file_type": "code", "source_file": "features/friends/presentation/friends_screen.dart", "source_location": null}, {"id": "friend", "label": "Friend", "file_type": "code", "source_file": null, "source_location": null}, {"id": "presentation_friends_screen_oninvite", "label": "onInvite", "file_type": "code", "source_file": "features/friends/presentation/friends_screen.dart", "source_location": null}, {"id": "voidcallback", "label": "VoidCallback", "file_type": "code", "source_file": null, "source_location": null}, {"id": "presentation_friends_screen_onremove", "label": "onRemove", "file_type": "code", "source_file": "features/friends/presentation/friends_screen.dart", "source_location": null}, {"id": "presentation_friends_screen_controller", "label": "_controller", "file_type": "code", "source_file": "features/friends/presentation/friends_screen.dart", "source_location": null}, {"id": "presentation_friends_screen_error", "label": "_error", "file_type": "code", "source_file": "features/friends/presentation/friends_screen.dart", "source_location": null}, {"id": "string", "label": "String?", "file_type": "code", "source_file": null, "source_location": null}, {"id": "presentation_friends_screen_add", "label": "_add", "file_type": "code", "source_file": "features/friends/presentation/friends_screen.dart", "source_location": null}, {"id": "presentation_friends_screen_build", "label": "build", "file_type": "code", "source_file": "features/friends/presentation/friends_screen.dart", "source_location": null}, {"id": "presentation_friends_screen_confirmremove", "label": "_confirmRemove", "file_type": "code", "source_file": "features/friends/presentation/friends_screen.dart", "source_location": null}, {"id": "presentation_friends_screen_createstate", "label": "createState", "file_type": "code", "source_file": "features/friends/presentation/friends_screen.dart", "source_location": null}, {"id": "presentation_friends_screen_dispose", "label": "dispose", "file_type": "code", "source_file": "features/friends/presentation/friends_screen.dart", "source_location": null}, {"id": "presentation_friends_screen_submit", "label": "_submit", "file_type": "code", "source_file": "features/friends/presentation/friends_screen.dart", "source_location": null}, {"id": "package_flutter_material_dart", "label": "package:flutter/material.dart", "file_type": "code", "source_file": null, "source_location": null}, {"id": "package_flutter_riverpod_flutter_riverpod_dart", "label": "package:flutter_riverpod/flutter_riverpod.dart", "file_type": "code", "source_file": null, "source_location": null}, {"id": "core_constants_insets_dart", "label": "../../../core/constants/insets.dart", "file_type": "code", "source_file": null, "source_location": null}, {"id": "core_constants_strings_dart", "label": "../../../core/constants/strings.dart", "file_type": "code", "source_file": null, "source_location": null}, {"id": "core_utils_code_gen_dart", "label": "../../../core/utils/code_gen.dart", "file_type": "code", "source_file": null, "source_location": null}, {"id": "core_utils_ui_feedback_dart", "label": "../../../core/utils/ui_feedback.dart", "file_type": "code", "source_file": null, "source_location": null}, {"id": "core_widgets_adaptive_scaffold_dart", "label": "../../../core/widgets/adaptive_scaffold.dart", "file_type": "code", "source_file": null, "source_location": null}, {"id": "core_widgets_async_view_dart", "label": "../../../core/widgets/async_view.dart", "file_type": "code", "source_file": null, "source_location": null}, {"id": "core_widgets_avatar_circle_dart", "label": "../../../core/widgets/avatar_circle.dart", "file_type": "code", "source_file": null, "source_location": null}, {"id": "core_widgets_status_views_dart", "label": "../../../core/widgets/status_views.dart", "file_type": "code", "source_file": null, "source_location": null}, {"id": "auth_presentation_auth_controller_dart", "label": "../../auth/presentation/auth_controller.dart", "file_type": "code", "source_file": null, "source_location": null}, {"id": "profile_presentation_widgets_friend_code_card_dart", "label": "../../profile/presentation/widgets/friend_code_card.dart", "file_type": "code", "source_file": null, "source_location": null}, {"id": "domain_friend_dart", "label": "../domain/friend.dart", "file_type": "code", "source_file": null, "source_location": null}, {"id": "friends_controller_dart", "label": "friends_controller.dart", "file_type": "code", "source_file": null, "source_location": null}], "edges": [{"source": "c_users_taraz_uno_family_lib_features_friends_presentation_friends_screen_dart", "target": "presentation_friends_screen_friendsscreen", "relation": "defines", "confidence": "EXTRACTED", "confidence_score": 1.0, "source_file": "features/friends/presentation/friends_screen.dart", "source_location": null, "weight": 1.0}, {"source": "presentation_friends_screen_friendsscreen", "target": "consumerwidget", "relation": "inherits", "confidence": "EXTRACTED", "confidence_score": 1.0, "source_file": "features/friends/presentation/friends_screen.dart", "source_location": null, "weight": 1.0}, {"source": "presentation_friends_screen_friendsscreen", "target": "friendscontrollerprovider", "relation": "references", "confidence": "EXTRACTED", "confidence_score": 1.0, "source_file": "features/friends/presentation/friends_screen.dart", "source_location": null, "weight": 1.0, "context": "riverpod_reference"}, {"source": "presentation_friends_screen_friendsscreen", "target": "friendscontrollerprovider", "relation": "references", "confidence": "EXTRACTED", "confidence_score": 1.0, "source_file": "features/friends/presentation/friends_screen.dart", "source_location": null, "weight": 1.0, "context": "riverpod_reference"}, {"source": "presentation_friends_screen_friendsscreen", "target": "authcontrollerprovider", "relation": "references", "confidence": "EXTRACTED", "confidence_score": 1.0, "source_file": "features/friends/presentation/friends_screen.dart", "source_location": null, "weight": 1.0, "context": "riverpod_reference"}, {"source": "presentation_friends_screen_friendsscreen", "target": "friendscontrollerprovider", "relation": "references", "confidence": "EXTRACTED", "confidence_score": 1.0, "source_file": "features/friends/presentation/friends_screen.dart", "source_location": null, "weight": 1.0, "context": "riverpod_reference"}, {"source": "c_users_taraz_uno_family_lib_features_friends_presentation_friends_screen_dart", "target": "presentation_friends_screen_friendtile", "relation": "defines", "confidence": "EXTRACTED", "confidence_score": 1.0, "source_file": "features/friends/presentation/friends_screen.dart", "source_location": null, "weight": 1.0}, {"source": "presentation_friends_screen_friendtile", "target": "statelesswidget", "relation": "inherits", "confidence": "EXTRACTED", "confidence_score": 1.0, "source_file": "features/friends/presentation/friends_screen.dart", "source_location": null, "weight": 1.0}, {"source": "c_users_taraz_uno_family_lib_features_friends_presentation_friends_screen_dart", "target": "presentation_friends_screen_addfrienddialog", "relation": "defines", "confidence": "EXTRACTED", "confidence_score": 1.0, "source_file": "features/friends/presentation/friends_screen.dart", "source_location": null, "weight": 1.0}, {"source": "presentation_friends_screen_addfrienddialog", "target": "statefulwidget", "relation": "inherits", "confidence": "EXTRACTED", "confidence_score": 1.0, "source_file": "features/friends/presentation/friends_screen.dart", "source_location": null, "weight": 1.0}, {"source": "c_users_taraz_uno_family_lib_features_friends_presentation_friends_screen_dart", "target": "presentation_friends_screen_addfrienddialogstate", "relation": "defines", "confidence": "EXTRACTED", "confidence_score": 1.0, "source_file": "features/friends/presentation/friends_screen.dart", "source_location": null, "weight": 1.0}, {"source": "presentation_friends_screen_addfrienddialogstate", "target": "state", "relation": "inherits", "confidence": "EXTRACTED", "confidence_score": 1.0, "source_file": "features/friends/presentation/friends_screen.dart", "source_location": null, "weight": 1.0}, {"source": "presentation_friends_screen_addfrienddialogstate", "target": "addfrienddialog", "relation": "references", "confidence": "EXTRACTED", "confidence_score": 1.0, "source_file": "features/friends/presentation/friends_screen.dart", "source_location": null, "weight": 1.0}, {"source": "c_users_taraz_uno_family_lib_features_friends_presentation_friends_screen_dart", "target": "presentation_friends_screen_friend", "relation": "defines", "confidence": "EXTRACTED", "confidence_score": 1.0, "source_file": "features/friends/presentation/friends_screen.dart", "source_location": null, "weight": 1.0}, {"source": "c_users_taraz_uno_family_lib_features_friends_presentation_friends_screen_dart", "target": "friend", "relation": "references", "confidence": "EXTRACTED", "confidence_score": 1.0, "source_file": "features/friends/presentation/friends_screen.dart", "source_location": null, "weight": 1.0, "context": "variable_type"}, {"source": "c_users_taraz_uno_family_lib_features_friends_presentation_friends_screen_dart", "target": "presentation_friends_screen_oninvite", "relation": "defines", "confidence": "EXTRACTED", "confidence_score": 1.0, "source_file": "features/friends/presentation/friends_screen.dart", "source_location": null, "weight": 1.0}, {"source": "c_users_taraz_uno_family_lib_features_friends_presentation_friends_screen_dart", "target": "voidcallback", "relation": "references", "confidence": "EXTRACTED", "confidence_score": 1.0, "source_file": "features/friends/presentation/friends_screen.dart", "source_location": null, "weight": 1.0, "context": "variable_type"}, {"source": "c_users_taraz_uno_family_lib_features_friends_presentation_friends_screen_dart", "target": "presentation_friends_screen_onremove", "relation": "defines", "confidence": "EXTRACTED", "confidence_score": 1.0, "source_file": "features/friends/presentation/friends_screen.dart", "source_location": null, "weight": 1.0}, {"source": "c_users_taraz_uno_family_lib_features_friends_presentation_friends_screen_dart", "target": "voidcallback", "relation": "references", "confidence": "EXTRACTED", "confidence_score": 1.0, "source_file": "features/friends/presentation/friends_screen.dart", "source_location": null, "weight": 1.0, "context": "variable_type"}, {"source": "c_users_taraz_uno_family_lib_features_friends_presentation_friends_screen_dart", "target": "presentation_friends_screen_controller", "relation": "defines", "confidence": "EXTRACTED", "confidence_score": 1.0, "source_file": "features/friends/presentation/friends_screen.dart", "source_location": null, "weight": 1.0}, {"source": "c_users_taraz_uno_family_lib_features_friends_presentation_friends_screen_dart", "target": "presentation_friends_screen_error", "relation": "defines", "confidence": "EXTRACTED", "confidence_score": 1.0, "source_file": "features/friends/presentation/friends_screen.dart", "source_location": null, "weight": 1.0}, {"source": "c_users_taraz_uno_family_lib_features_friends_presentation_friends_screen_dart", "target": "string", "relation": "references", "confidence": "EXTRACTED", "confidence_score": 1.0, "source_file": "features/friends/presentation/friends_screen.dart", "source_location": null, "weight": 1.0, "context": "variable_type"}, {"source": "c_users_taraz_uno_family_lib_features_friends_presentation_friends_screen_dart", "target": "presentation_friends_screen_add", "relation": "defines", "confidence": "EXTRACTED", "confidence_score": 1.0, "source_file": "features/friends/presentation/friends_screen.dart", "source_location": null, "weight": 1.0}, {"source": "presentation_friends_screen_add", "target": "friendscontrollerprovider", "relation": "references", "confidence": "EXTRACTED", "confidence_score": 1.0, "source_file": "features/friends/presentation/friends_screen.dart", "source_location": null, "weight": 1.0, "context": "riverpod_reference"}, {"source": "c_users_taraz_uno_family_lib_features_friends_presentation_friends_screen_dart", "target": "presentation_friends_screen_build", "relation": "defines", "confidence": "EXTRACTED", "confidence_score": 1.0, "source_file": "features/friends/presentation/friends_screen.dart", "source_location": null, "weight": 1.0}, {"source": "presentation_friends_screen_build", "target": "friendscontrollerprovider", "relation": "references", "confidence": "EXTRACTED", "confidence_score": 1.0, "source_file": "features/friends/presentation/friends_screen.dart", "source_location": null, "weight": 1.0, "context": "riverpod_reference"}, {"source": "presentation_friends_screen_build", "target": "authcontrollerprovider", "relation": "references", "confidence": "EXTRACTED", "confidence_score": 1.0, "source_file": "features/friends/presentation/friends_screen.dart", "source_location": null, "weight": 1.0, "context": "riverpod_reference"}, {"source": "c_users_taraz_uno_family_lib_features_friends_presentation_friends_screen_dart", "target": "presentation_friends_screen_confirmremove", "relation": "defines", "confidence": "EXTRACTED", "confidence_score": 1.0, "source_file": "features/friends/presentation/friends_screen.dart", "source_location": null, "weight": 1.0}, {"source": "presentation_friends_screen_confirmremove", "target": "friendscontrollerprovider", "relation": "references", "confidence": "EXTRACTED", "confidence_score": 1.0, "source_file": "features/friends/presentation/friends_screen.dart", "source_location": null, "weight": 1.0, "context": "riverpod_reference"}, {"source": "c_users_taraz_uno_family_lib_features_friends_presentation_friends_screen_dart", "target": "presentation_friends_screen_friendtile", "relation": "defines", "confidence": "EXTRACTED", "confidence_score": 1.0, "source_file": "features/friends/presentation/friends_screen.dart", "source_location": null, "weight": 1.0}, {"source": "c_users_taraz_uno_family_lib_features_friends_presentation_friends_screen_dart", "target": "presentation_friends_screen_build", "relation": "defines", "confidence": "EXTRACTED", "confidence_score": 1.0, "source_file": "features/friends/presentation/friends_screen.dart", "source_location": null, "weight": 1.0}, {"source": "c_users_taraz_uno_family_lib_features_friends_presentation_friends_screen_dart", "target": "presentation_friends_screen_addfrienddialog", "relation": "defines", "confidence": "EXTRACTED", "confidence_score": 1.0, "source_file": "features/friends/presentation/friends_screen.dart", "source_location": null, "weight": 1.0}, {"source": "c_users_taraz_uno_family_lib_features_friends_presentation_friends_screen_dart", "target": "presentation_friends_screen_createstate", "relation": "defines", "confidence": "EXTRACTED", "confidence_score": 1.0, "source_file": "features/friends/presentation/friends_screen.dart", "source_location": null, "weight": 1.0}, {"source": "c_users_taraz_uno_family_lib_features_friends_presentation_friends_screen_dart", "target": "presentation_friends_screen_dispose", "relation": "defines", "confidence": "EXTRACTED", "confidence_score": 1.0, "source_file": "features/friends/presentation/friends_screen.dart", "source_location": null, "weight": 1.0}, {"source": "c_users_taraz_uno_family_lib_features_friends_presentation_friends_screen_dart", "target": "presentation_friends_screen_submit", "relation": "defines", "confidence": "EXTRACTED", "confidence_score": 1.0, "source_file": "features/friends/presentation/friends_screen.dart", "source_location": null, "weight": 1.0}, {"source": "c_users_taraz_uno_family_lib_features_friends_presentation_friends_screen_dart", "target": "presentation_friends_screen_build", "relation": "defines", "confidence": "EXTRACTED", "confidence_score": 1.0, "source_file": "features/friends/presentation/friends_screen.dart", "source_location": null, "weight": 1.0}, {"source": "c_users_taraz_uno_family_lib_features_friends_presentation_friends_screen_dart", "target": "package_flutter_material_dart", "relation": "imports", "confidence": "EXTRACTED", "confidence_score": 1.0, "source_file": "features/friends/presentation/friends_screen.dart", "source_location": null, "weight": 1.0}, {"source": "c_users_taraz_uno_family_lib_features_friends_presentation_friends_screen_dart", "target": "package_flutter_riverpod_flutter_riverpod_dart", "relation": "imports", "confidence": "EXTRACTED", "confidence_score": 1.0, "source_file": "features/friends/presentation/friends_screen.dart", "source_location": null, "weight": 1.0}, {"source": "c_users_taraz_uno_family_lib_features_friends_presentation_friends_screen_dart", "target": "core_constants_insets_dart", "relation": "imports", "confidence": "EXTRACTED", "confidence_score": 1.0, "source_file": "features/friends/presentation/friends_screen.dart", "source_location": null, "weight": 1.0}, {"source": "c_users_taraz_uno_family_lib_features_friends_presentation_friends_screen_dart", "target": "core_constants_strings_dart", "relation": "imports", "confidence": "EXTRACTED", "confidence_score": 1.0, "source_file": "features/friends/presentation/friends_screen.dart", "source_location": null, "weight": 1.0}, {"source": "c_users_taraz_uno_family_lib_features_friends_presentation_friends_screen_dart", "target": "core_utils_code_gen_dart", "relation": "imports", "confidence": "EXTRACTED", "confidence_score": 1.0, "source_file": "features/friends/presentation/friends_screen.dart", "source_location": null, "weight": 1.0}, {"source": "c_users_taraz_uno_family_lib_features_friends_presentation_friends_screen_dart", "target": "core_utils_ui_feedback_dart", "relation": "imports", "confidence": "EXTRACTED", "confidence_score": 1.0, "source_file": "features/friends/presentation/friends_screen.dart", "source_location": null, "weight": 1.0}, {"source": "c_users_taraz_uno_family_lib_features_friends_presentation_friends_screen_dart", "target": "core_widgets_adaptive_scaffold_dart", "relation": "imports", "confidence": "EXTRACTED", "confidence_score": 1.0, "source_file": "features/friends/presentation/friends_screen.dart", "source_location": null, "weight": 1.0}, {"source": "c_users_taraz_uno_family_lib_features_friends_presentation_friends_screen_dart", "target": "core_widgets_async_view_dart", "relation": "imports", "confidence": "EXTRACTED", "confidence_score": 1.0, "source_file": "features/friends/presentation/friends_screen.dart", "source_location": null, "weight": 1.0}, {"source": "c_users_taraz_uno_family_lib_features_friends_presentation_friends_screen_dart", "target": "core_widgets_avatar_circle_dart", "relation": "imports", "confidence": "EXTRACTED", "confidence_score": 1.0, "source_file": "features/friends/presentation/friends_screen.dart", "source_location": null, "weight": 1.0}, {"source": "c_users_taraz_uno_family_lib_features_friends_presentation_friends_screen_dart", "target": "core_widgets_status_views_dart", "relation": "imports", "confidence": "EXTRACTED", "confidence_score": 1.0, "source_file": "features/friends/presentation/friends_screen.dart", "source_location": null, "weight": 1.0}, {"source": "c_users_taraz_uno_family_lib_features_friends_presentation_friends_screen_dart", "target": "auth_presentation_auth_controller_dart", "relation": "imports", "confidence": "EXTRACTED", "confidence_score": 1.0, "source_file": "features/friends/presentation/friends_screen.dart", "source_location": null, "weight": 1.0}, {"source": "c_users_taraz_uno_family_lib_features_friends_presentation_friends_screen_dart", "target": "profile_presentation_widgets_friend_code_card_dart", "relation": "imports", "confidence": "EXTRACTED", "confidence_score": 1.0, "source_file": "features/friends/presentation/friends_screen.dart", "source_location": null, "weight": 1.0}, {"source": "c_users_taraz_uno_family_lib_features_friends_presentation_friends_screen_dart", "target": "domain_friend_dart", "relation": "imports", "confidence": "EXTRACTED", "confidence_score": 1.0, "source_file": "features/friends/presentation/friends_screen.dart", "source_location": null, "weight": 1.0}, {"source": "c_users_taraz_uno_family_lib_features_friends_presentation_friends_screen_dart", "target": "friends_controller_dart", "relation": "imports", "confidence": "EXTRACTED", "confidence_score": 1.0, "source_file": "features/friends/presentation/friends_screen.dart", "source_location": null, "weight": 1.0}]}